jder_fastapi/__init__.py
jder_fastapi/handlers/__init__.py
jder_fastapi/handlers/py.typed
jder_fastapi/handlers/validation/__init__.py
jder_fastapi/handlers/validation/main.py
jder_fastapi/handlers/validation/py.typed
jder_fastapi/py.typed
jder_fastapi/responses/__init__.py
jder_fastapi/responses/error/__init__.py
jder_fastapi/responses/error/main.py
jder_fastapi/responses/error/py.typed
jder_fastapi/responses/json/__init__.py
jder_fastapi/responses/json/main.py
jder_fastapi/responses/json/py.typed
jder_fastapi/responses/main.py
jder_fastapi/responses/py.typed
jder_fastapi-0.2.1.dist-info/WHEEL
jder_fastapi-0.2.1.dist-info/METADATA
jder_fastapi-0.2.1.dist-info/RECORD
