Metadata-Version: 2.4
Name: jder-fastapi
Version: 0.2.1
Summary: A response builder for FastAPI
Keywords: jder,json,response,fastapi,python
Author: Alpheus
Author-email: Alpheus <contact@alphe.us>
License-Expression: MIT
Classifier: Topic :: File Formats
Classifier: Topic :: File Formats :: JSON
Classifier: Topic :: File Formats :: JSON :: JSON Schema
Classifier: Framework :: FastAPI
Classifier: Programming Language :: Python :: 3.13
Classifier: Programming Language :: Python :: 3.14
Classifier: Programming Language :: Python :: 3.15
Requires-Dist: fastapi>=0.116.0,<0.129.0
Requires-Python: >=3.13, <4.0
Project-URL: Changelog, https://github.com/jderstd/fastapi/blob/main/package/CHANGELOG.md
Project-URL: Documentation, https://github.com/jderstd/fastapi/blob/main/docs/README.md
Project-URL: Homepage, https://github.com/jderstd/fastapi
Project-URL: Issues, https://github.com/jderstd/fastapi/issues
Project-URL: Repository, https://github.com/jderstd/fastapi
